FrcApi/__init__.py
FrcApi/config.py
FrcApi/district_ranking_calculation.py
FrcApi/fun.py
FrcApi/matchresults.py
FrcApi/rankings.py
FrcApi/seasondata.py
frc_api-1.0.1.dist-info/LICENSE
frc_api-1.0.1.dist-info/METADATA
frc_api-1.0.1.dist-info/WHEEL
frc_api-1.0.1.dist-info/top_level.txt
frc_api-1.0.1.dist-info/RECORD
