Metadata-Version: 2.1
Name: frc-api
Version: 1.0.1
Summary: A wrapper for the FRC events api
Author-email: Cole Kauder-McMurrich <gamingwithcole7@gmail.com>
License: GNU GENERAL PUBLIC LICENSE
Project-URL: Homepage, https://github.com/Colepng/FRC-API/tree/main
Project-URL: Bug Tracker, https://github.com/Colepng/FRC-API/issues
Classifier: Programming Language :: Python :: 3.11
Classifier: License :: OSI Approved
Classifier: Operating System :: OS Independent
Classifier: Development Status :: 5 - Production/Stable
Classifier: Intended Audience :: Developers
Classifier: Natural Language :: English
Requires-Python: >=3.8
License-File: LICENSE
